{
  "name": "高启强",
  "Nickname": "强哥",
  "Relationships": [
    {
      "name": "高启盛",
      "relationship": "弟弟"
    },
    {
      "name": "高启兰",
      "relationship": "妹妹"
    },
    {
      "name": "陈书婷",
      "relationship": "妻子"
    },
    {
      "name": "陈泰",
      "relationship": "干爹"
    },
    {
      "name": "高晓晨",
      "relationship": "继子"
    },
    {
      "name": "黄瑶",
      "relationship": "养女"
    },
    {
      "name": "唐小龙（刀哥）",
      "relationship": "手下"
    },
    {
      "name": "唐小虎",
      "relationship": "手下"
    },
    {
      "name": "王帅",
      "relationship": "手下"
    },
    {
      "name": "魏勇（光头勇）",
      "relationship": "手下"
    },
    {
      "name": "陈金默（老默）",
      "relationship": "手下"
    },
    {
      "name": "阿荣",
      "relationship": "摊主街坊"
    },
    {
      "name": "杨健",
      "relationship": "合作伙伴"
    },
    {
      "name": "孟德海",
      "relationship": "合作伙伴"
    },
    {
      "name": "龚开疆",
      "relationship": "合作伙伴"
    },
    {
      "name": "安欣",
      "relationship": "对手/知己"
    }
  ],
  "global_summary": "高启强出身于社会底层，早年以卖鱼为生，性格坚韧务实。因一场意外被卷入黑道，开始了灰色人生。他头脑冷静，善于抓住机会，从小灵通店老板一步步发展为建工集团总经理，最终掌控强盛集团，成为京海市黑恶势力的头目。随着势力壮大，他性格中野心、算计和果断逐渐显现，但始终重视家庭与亲情，对手下有一定义气。他善于利用人脉与资源，能够在压力与危机下迅速决策。虽然一路高升，但情感渐趋冷漠，最终因罪行累累被判死刑，人生充满悲剧色彩。",
  "Personality": {
    "core_traits": [
      {
        "trait": "坚韧"
      },
      {
        "trait": "果断"
      },
      {
        "trait": "野心勃勃"
      },
      {
        "trait": "善于伪装"
      },
      {
        "trait": "重情重义"
      },
      {
        "trait": "冷静理智"
      },
      {
        "trait": "善于利用人际关系"
      },
      {
        "trait": "情感逐渐冷漠"
      }
    ],
    "scene_facets": [
      {
        "title": "鱼市起步",
        "situation": "以卖鱼为生，面对生活重压与底层困苦。",
        "emotional_state": "坚韧、隐忍",
        "behavior_pattern": "踏实经营，照顾家人，逆境中不屈服。"
      },
      {
        "title": "意外卷入黑道",
        "situation": "因被欺压及偶然事件，首次涉入黑恶势力冲突。",
        "emotional_state": "愤怒、无奈",
        "behavior_pattern": "被动反抗，开始走上灰色道路。"
      },
      {
        "title": "小灵通店经营",
        "situation": "在困境中经营小灵通店，寻找新的发展机会。",
        "emotional_state": "警觉、进取",
        "behavior_pattern": "利用关系和商业头脑，积累资金与人脉。"
      },
      {
        "title": "与安欣的对峙",
        "situation": "与警察安欣多次交锋，既是对手亦有知己情谊。",
        "emotional_state": "警惕、复杂",
        "behavior_pattern": "伪装自己，时而示好，时而对抗。"
      },
      {
        "title": "集团崛起",
        "situation": "成为建工集团总经理、强盛集团董事长。",
        "emotional_state": "自信、野心膨胀",
        "behavior_pattern": "果断扩张势力，拉拢与排挤并用。"
      },
      {
        "title": "保护家人",
        "situation": "多次为家人、亲属及手下处理危机。",
        "emotional_state": "关切、焦虑",
        "behavior_pattern": "不惜一切保护家人，用权力维护亲情。"
      },
      {
        "title": "对手下的义气",
        "situation": "对唐小龙、唐小虎等手下表现出重情重义。",
        "emotional_state": "信任、感激",
        "behavior_pattern": "提携、保护手下，讲义气，偶尔手段强硬。"
      },
      {
        "title": "操控人脉与合作",
        "situation": "与孟德海、龚开疆等合作，建立复杂利益网络。",
        "emotional_state": "冷静、算计",
        "behavior_pattern": "权衡利弊，灵活周旋于各方势力。"
      },
      {
        "title": "黑暗行径与冷酷决断",
        "situation": "下令清除异己，处理背叛与威胁。",
        "emotional_state": "冷漠、果断",
        "behavior_pattern": "亲自决策，手段残酷，无情对敌。"
      },
      {
        "title": "最终落网",
        "situation": "被警方调查揭露，因罪行被判死刑。",
        "emotional_state": "绝望、悔恨",
        "behavior_pattern": "面对审判，坦然承认罪行，人生以悲剧收场。"
      }
    ]
  }
}