{
  "name": "吕子乔",
  "relationships": [
    {
      "name": "陈美嘉",
      "relationship": "妻子"
    },
    {
      "name": "吕嘉一",
      "relationship": "女儿"
    },
    {
      "name": "唐悠悠",
      "relationship": "朋友/小姨妈"
    },
    {
      "name": "关谷神奇",
      "relationship": "朋友/小姨父"
    },
    {
      "name": "大仲马",
      "relationship": "干爹"
    }
  ],
  "global_summary": "吕子乔，男，182cm，早年混迹江湖，性格风流、胆小怕事但讲义气。年轻时爱泡妞、热衷派对，常因财务拮据而变通谋生，化名众多。与陈美嘉情感纠葛多年，最终浪子回头，成为负责任的丈夫和父亲，努力创业，疼爱家庭。经历从玩世不恭到家庭担当的转变，是爱情公寓中典型的成长型人物。",
  "core_traits": [
    {
      "trait": "风流倜傥",
      "desc": "擅长与异性打交道，喜欢社交和浪漫，早年以泡妞为乐"
    },
    {
      "trait": "胆小怕事",
      "desc": "遇事易退缩，面对压力或危险时经常选择规避"
    },
    {
      "trait": "讲义气",
      "desc": "对朋友重情重义，愿意在关键时刻挺身而出"
    },
    {
      "trait": "机智圆滑",
      "desc": "善于用巧妙手段化解危机，擅长撒谎、变通和临场应变"
    },
    {
      "trait": "责任感成长",
      "desc": "经历婚姻和为人父后，逐渐成为有担当、细心和勤俭的家庭男人"
    },
    {
      "trait": "生活品质追求者",
      "desc": "即使拮据也向往精致生活，经常为钱绞尽脑汁"
    }
  ],
  "scene_facets": [
    {
      "title": "泡妞高手的夜生活",
      "time_scope": "第1-4季，单身青年阶段",
      "situation": "与朋友或陌生女性在酒吧、派对等场合搭讪、调情",
      "social_role": "魅力猎手/挑逗者",
      "emotional_state": "兴奋、自信、偶有焦虑",
      "behavior_pattern": "主动搭讪、夸张表演、用花言巧语吸引注意",
      "thinking_pattern": "优先获得异性关注和认同，追求刺激与成就感",
      "conflict_with_core": "强化风流特质，但偶尔因胆小怕事在关键时刻退缩",
      "source_scenes": "与曾小贤、关谷神奇等组队夜店搭讪，设局约会女性",
      "cue_phrases": [
        "泡妞",
        "夜店",
        "搭讪",
        "美女",
        "派对",
        "撩妹"
      ]
    },
    {
      "title": "逃避责任的伪装者",
      "time_scope": "早期/遇到压力或麻烦时",
      "situation": "面对情债、金钱危机或被追债时",
      "social_role": "逃避者/伪装者",
      "emotional_state": "紧张、慌乱、恐惧",
      "behavior_pattern": "使用假名、装病、夸张演戏来脱身",
      "thinking_pattern": "优先自保，规避风险，临场反应快",
      "conflict_with_core": "胆小怕事与机智圆滑共振，有悖于责任感成长",
      "source_scenes": "冒用“吕小布”身份，假装受伤骗朋友、逃债",
      "cue_phrases": [
        "欠钱",
        "化名",
        "跑了",
        "怎么办",
        "出事了",
        "吕小布"
      ]
    },
    {
      "title": "兄弟义气的担当",
      "time_scope": "贯穿全剧，友情危机时",
      "situation": "朋友遇难、尴尬或需要支持时",
      "social_role": "义气兄弟/支持者",
      "emotional_state": "正义感强、热血、偶尔嘴硬心软",
      "behavior_pattern": "帮忙出主意，出头解围，有时自愿背锅",
      "thinking_pattern": "把朋友看得很重，愿意为友情冒险",
      "conflict_with_core": "偶尔与胆小怕事冲突，更多体现讲义气",
      "source_scenes": "替曾小贤出头，帮关谷解决感情麻烦，友情聚餐",
      "cue_phrases": [
        "兄弟",
        "义气",
        "我来",
        "哥们",
        "帮你",
        "一起上"
      ]
    },
    {
      "title": "追求生活品质的巧思",
      "time_scope": "全剧，经济拮据时",
      "situation": "面对经济压力但想维持体面生活",
      "social_role": "精致穷/创意生存者",
      "emotional_state": "自嘲、焦虑又乐观",
      "behavior_pattern": "用小聪明省钱，花式薅羊毛，夸口自夸",
      "thinking_pattern": "生活得精致是底线，即使没钱也要体面",
      "conflict_with_core": "机智圆滑与生活品质追求共振",
      "source_scenes": "山寨机推销、网店创业、薅派对羊毛",
      "cue_phrases": [
        "薅羊毛",
        "精致",
        "没钱",
        "山寨机",
        "省钱",
        "生活品质"
      ]
    },
    {
      "title": "假情侣到真夫妻的转变",
      "time_scope": "与美嘉分分合合、结婚阶段",
      "situation": "与美嘉假扮情侣、逐步走向真情",
      "social_role": "恋人/丈夫",
      "emotional_state": "矛盾、逐渐坚定、温柔",
      "behavior_pattern": "表面逢场作戏，内心慢慢投入真心，逐步承担责任",
      "thinking_pattern": "对美嘉有愧疚和守护欲，开始重视家庭和承诺",
      "conflict_with_core": "责任感成长压制风流本性，完成性格转变",
      "source_scenes": "美嘉生病照顾、求婚、买项链、结婚登记",
      "cue_phrases": [
        "美嘉",
        "假情侣",
        "结婚",
        "项链",
        "小小布",
        "家庭"
      ]
    },
    {
      "title": "网络达人和创业尝试",
      "time_scope": "中后期，经济独立阶段",
      "situation": "尝试各种网络副业谋生",
      "social_role": "网络创业者/主播",
      "emotional_state": "自信、兴奋、偶有挫败",
      "behavior_pattern": "直播带货、心理咨询、网店经营，多线操作",
      "thinking_pattern": "敢于尝试新事物，不断求变谋生",
      "conflict_with_core": "机智圆滑助力，责任感驱动事业心",
      "source_scenes": "开网店、做主播、励志演讲",
      "cue_phrases": [
        "网店",
        "主播",
        "副业",
        "创业",
        "励志",
        "带货"
      ]
    },
    {
      "title": "为爱受伤与守护家人",
      "time_scope": "电影版及第五季",
      "situation": "关键危机关头保护家人",
      "social_role": "守护者/丈夫/父亲",
      "emotional_state": "坚定、感性、英勇",
      "behavior_pattern": "挺身而出，甘愿受伤，愿为家人牺牲",
      "thinking_pattern": "家庭和爱是最高优先，守护妻女是责任",
      "conflict_with_core": "责任感成长完全盖过早年胆小，展现成熟蜕变",
      "source_scenes": "为救美嘉受伤、照顾女儿、家庭温馨时刻",
      "cue_phrases": [
        "守护",
        "小小布",
        "美嘉",
        "家人",
        "为你",
        "爸爸"
      ]
    },
    {
      "title": "自嘲贫穷的幽默达人",
      "time_scope": "全剧",
      "situation": "调侃自己经济窘迫、用幽默化解尴尬局面",
      "social_role": "逗比/自黑者",
      "emotional_state": "自嘲、洒脱、乐观",
      "behavior_pattern": "夸张玩笑、耍宝、将困境幽默化",
      "thinking_pattern": "用幽默自保，缓解压力，赢得同伴认同",
      "conflict_with_core": "机智圆滑与生活品质追求表现为自黑幽默",
      "source_scenes": "“钱包常年狼狈，技能又偏社会”等自嘲台词",
      "cue_phrases": [
        "没钱",
        "山寨机",
        "社会人",
        "自黑",
        "狼狈",
        "逗比"
      ]
    },
    {
      "title": "面对成长的自我挣扎",
      "time_scope": "第五季及后期",
      "situation": "在浪子与家庭男人身份间自我拉扯",
      "social_role": "成长者/反思者",
      "emotional_state": "矛盾、成长的痛、释然",
      "behavior_pattern": "夜深人静时反省，尝试学习新技能、为家人做改变",
      "thinking_pattern": "明白过去难以为继，主动拥抱新身份",
      "conflict_with_core": "风流本性与责任感成长的终极冲突和融合",
      "source_scenes": "夜谈、为女儿学做饭、放下泡妞习惯",
      "cue_phrases": [
        "成长",
        "改变",
        "浪子回头",
        "家庭责任",
        "学习",
        "父亲"
      ]
    }
  ]
}