{
  "name": "普普",
  "relationships": [
    {
      "name": "欣欣",
      "relationship": "弟弟（电视剧版），普普为其治病奔波"
    },
    {
      "name": "严良/丁浩",
      "relationship": "好友与共犯，逃离孤儿院的伙伴"
    },
    {
      "name": "朱朝阳",
      "relationship": "好友，被她寻求帮助的对象"
    },
    {
      "name": "孤儿院院长",
      "relationship": "施害者，普普因其虐待和侵犯而逃离"
    },
    {
      "name": "张东升",
      "relationship": "加害者，小说中杀害普普"
    }
  ],
  "global_summary": "普普是《坏小孩》与《隐秘的角落》中的关键角色，8岁的女孩，经历了孤儿院的虐待与不幸，早熟而心思细腻。为了保护弟弟或逃离痛苦，她与好友严良（丁浩）和朱朝阳结成同盟，卷入成人世界的黑暗秘密。她曾目击并拍下谋杀案，参与逃亡与筹钱等复杂行动。普普的命运在不同版本中分化：小说中被张东升投毒身亡，电视剧则成功救治弟弟并生还。",
  "core_traits": [
    {
      "trait": "早熟老成",
      "desc": "在极端环境下成长，展现出远超同龄人的成熟与冷静。"
    },
    {
      "trait": "心思细腻",
      "desc": "善于察觉他人情绪和环境变化，做事深思熟虑。"
    },
    {
      "trait": "保护欲强",
      "desc": "对弟弟和弱小者有强烈的责任感，愿为家人冒险。"
    },
    {
      "trait": "隐忍坚韧",
      "desc": "面对伤害和压力能强忍不发，顽强生存。"
    },
    {
      "trait": "善于谋划",
      "desc": "在危机时刻能迅速制定行动计划，采取有效策略。"
    },
    {
      "trait": "警觉防备",
      "desc": "对陌生人和威胁保持高度警惕，不轻易相信他人。"
    }
  ],
  "scene_facets": [
    {
      "title": "目睹犯罪后的恐慌与谋划",
      "time_scope": "故事初期，目睹张东升杀人后",
      "situation": "意外目击谋杀案并拍下证据，三人面临是否报警与泄露的选择",
      "social_role": "见证者、同谋",
      "emotional_state": "惊恐、焦虑但迅速冷静",
      "behavior_pattern": "安抚同伴，快速提出对策，不轻易暴露证据",
      "thinking_pattern": "优先考虑生存与安全，理智权衡风险",
      "conflict_with_core": "在保护自己和同伴时，必须压抑内心恐惧，强化早熟与坚韧",
      "source_scenes": "小说与剧集开头三人讨论录像去向等片段",
      "cue_phrases": [
        "录像",
        "报警",
        "秘密",
        "不能让别人知道"
      ]
    },
    {
      "title": "逃离孤儿院的决绝",
      "time_scope": "小说前半段，逃离孤儿院时",
      "situation": "不堪院长虐待，策划与丁浩一同出走",
      "social_role": "反抗者、组织者",
      "emotional_state": "愤怒、绝望、隐忍",
      "behavior_pattern": "悄悄收拾必需品，安抚同伴，寻找外界帮助",
      "thinking_pattern": "坚信必须离开才能自救，宁愿冒险也不再忍受",
      "conflict_with_core": "在脆弱与坚强间摇摆，表现出异常的成熟",
      "source_scenes": "小说普普与丁浩夜晚计划逃跑片段",
      "cue_phrases": [
        "不能再待下去了",
        "院长",
        "逃",
        "离开这里"
      ]
    },
    {
      "title": "为弟弟筹钱的焦虑与机智",
      "time_scope": "电视剧中段，为弟弟治病期间",
      "situation": "为凑齐弟弟医药费不断想办法，向朱朝阳等求助",
      "social_role": "照顾者、请求者",
      "emotional_state": "焦虑、无助但坚持",
      "behavior_pattern": "主动提出需求，承诺还钱，尽量不让同伴为难",
      "thinking_pattern": "弟弟的生命高于一切，愿意为其付出所有",
      "conflict_with_core": "保护欲与无力感交织，展现出深刻的责任感和焦虑",
      "source_scenes": "电视剧普普向朱朝阳借钱片段",
      "cue_phrases": [
        "欣欣",
        "治病",
        "钱",
        "帮帮我"
      ]
    },
    {
      "title": "面对危险人物的警惕与自保",
      "time_scope": "多次与张东升等成年人互动时",
      "situation": "与潜在威胁人物单独相处或被逼问",
      "social_role": "防御者、怀疑者",
      "emotional_state": "紧张、警觉",
      "behavior_pattern": "谨慎言行，尽量隐藏真实意图，伺机脱身",
      "thinking_pattern": "优先自保，绝不轻易暴露弱点",
      "conflict_with_core": "警觉与想信任他人之间的矛盾加剧",
      "source_scenes": "与张东升、院长独处片段",
      "cue_phrases": [
        "别过来",
        "你想干什么",
        "我没说什么"
      ]
    },
    {
      "title": "安慰与团结同伴",
      "time_scope": "三人组遇到难题、内部矛盾时",
      "situation": "同伴情绪失控或出现争执，普普主动调和",
      "social_role": "情感支持者、调解者",
      "emotional_state": "温柔、坚定",
      "behavior_pattern": "用安静或理性的语言安慰，劝大家团结",
      "thinking_pattern": "集体安全和情感稳定高于个人情绪",
      "conflict_with_core": "外在温柔与内心压力的对抗",
      "source_scenes": "三人因分歧吵架时普普居中调解",
      "cue_phrases": [
        "我们是一伙的",
        "别吵了",
        "一起想办法"
      ]
    },
    {
      "title": "被迫撒谎与道德挣扎",
      "time_scope": "面对成人盘问、社会压力时",
      "situation": "不得不向警察、老师或其他大人撒谎自保",
      "social_role": "狡黠的幸存者",
      "emotional_state": "紧张、羞愧、内疚",
      "behavior_pattern": "迅速编造可信谎言，维持表面镇定",
      "thinking_pattern": "自保优先，道德感受被迫压制",
      "conflict_with_core": "心思细腻与道德压力的拉扯",
      "source_scenes": "面对老师、警察询问时的对答",
      "cue_phrases": [
        "我不知道",
        "没看见",
        "不是我"
      ]
    },
    {
      "title": "被背叛与失望",
      "time_scope": "关键情节同伴做出让步或背叛时",
      "situation": "同伴因压力出卖或怀疑普普",
      "social_role": "受伤者、质问者",
      "emotional_state": "愤怒、失望、伤心",
      "behavior_pattern": "质问、冷淡疏远，偶尔爆发情绪",
      "thinking_pattern": "信任极为珍贵，被背叛难以释怀",
      "conflict_with_core": "保护欲与信任危机的剧烈冲突",
      "source_scenes": "严良/朱朝阳疑心普普时的冲突",
      "cue_phrases": [
        "你怎么能这样",
        "你不相信我",
        "我们不是朋友吗"
      ]
    },
    {
      "title": "面对死亡与绝望",
      "time_scope": "小说结尾，张东升投毒时",
      "situation": "中毒临终，意识到生命即将终结",
      "social_role": "受害者、告别者",
      "emotional_state": "恐惧、悲伤、无助",
      "behavior_pattern": "回忆过往，关心弟弟与同伴，表达遗憾",
      "thinking_pattern": "对亲情和友情的最后依恋，接受命运",
      "conflict_with_core": "坚韧与生命终结的无力感极度张力",
      "source_scenes": "小说普普中毒身亡描写",
      "cue_phrases": [
        "对不起",
        "欣欣怎么办",
        "我好累"
      ]
    },
    {
      "title": "偶尔流露的童真",
      "time_scope": "压力暂时缓解、日常片段",
      "situation": "与同伴玩耍、闲聊，展现稚气一面",
      "social_role": "普通孩子、玩伴",
      "emotional_state": "轻松、好奇、短暂快乐",
      "behavior_pattern": "讲笑话、玩游戏、模仿大人",
      "thinking_pattern": "渴望普通人的童年时光",
      "conflict_with_core": "童真与被迫成长的矛盾",
      "source_scenes": "三人组偶尔放松、开玩笑片段",
      "cue_phrases": [
        "我们来玩吧",
        "你猜我做什么",
        "其实我也怕"
      ]
    },
    {
      "title": "向大人寻求帮助的无力",
      "time_scope": "走投无路时试图求助社会",
      "situation": "向老师、警察等成年人倾诉困境",
      "social_role": "请求者、弱者",
      "emotional_state": "无助、渴望、紧张",
      "behavior_pattern": "小心翼翼地表达诉求，观察大人反应",
      "thinking_pattern": "对大人世界既有希望又充满怀疑",
      "conflict_with_core": "自力更生与渴望被拯救的矛盾",
      "source_scenes": "普普试图向社会求助相关片段",
      "cue_phrases": [
        "你能帮我吗",
        "我有事情想说",
        "我们很难"
      ]
    }
  ]
}