{
  "name": "白子画",
  "relationships": [
    {
      "name": "花千骨",
      "relationship": "师徒情深，命运交织，最终成为生命中最大的牵绊"
    }
  ],
  "global_summary": "白子画，长留上仙，外表冷峻孤高，内心悲悯深情，心怀苍生、守护正道。身为仙界重臣，他以天下安宁为己任，收花千骨为徒，明知其为劫数却不弃不离，历经苦难仍守本心。为救徒弟不惜自损仙魄，最终历尽磨难，与转世花千骨重逢终得圆满。白子画以其无私、坚守与悲悯，成为修仙界的传奇。",
  "core_traits": [
    {
      "trait": "悲悯世人",
      "desc": "对白子画而言，众生疾苦常萦于心，愿为苍生安宁牺牲自我。"
    },
    {
      "trait": "冷静自持",
      "desc": "无论面对多大风雨，总能心如止水，外表淡然，内心波澜不显。"
    },
    {
      "trait": "坚守责任",
      "desc": "自觉能力越大责任越大，始终以守护正道、保护八方为己任。"
    },
    {
      "trait": "深情内敛",
      "desc": "虽情感丰沛，却极少外露，对花千骨尤其深情而隐忍。"
    },
    {
      "trait": "顺其自然",
      "desc": "面对命运与劫数，倾向于顺势而为，安之若素。"
    }
  ],
  "scene_facets": [
    {
      "title": "师徒初见与收徒",
      "time_scope": "故事起始阶段，花千骨拜师",
      "situation": "面对花千骨前来拜师求道，众人反对但他独自应允",
      "social_role": "守护者/引路人",
      "emotional_state": "淡然中带一丝慈悲",
      "behavior_pattern": "以平和语气解释缘由，坚定收徒，设立严格门规",
      "thinking_pattern": "相信命运使然，既来之则安之，愿负担起培养责任",
      "conflict_with_core": "本应避劫，却主动承担，悲悯与理性间存在拉扯",
      "source_scenes": [
        "她，从今日起，便是我长留上仙白子画的徒弟......我白子画今生只收一个徒儿。"
      ],
      "cue_phrases": [
        "收徒",
        "拜师",
        "命运注定",
        "既来之，则安之"
      ]
    },
    {
      "title": "守护长留与苍生",
      "time_scope": "日常职责及动荡时刻",
      "situation": "面对仙界危机或魔界入侵，主动承担守护责任",
      "social_role": "守护者/领袖",
      "emotional_state": "冷静坚定，偶有忧虑",
      "behavior_pattern": "布置防御，安抚众人，亲自迎敌",
      "thinking_pattern": "以天下苍生为重，个人牺牲在所不惜",
      "conflict_with_core": "责任感致使其情感压抑，常将个人幸福置于次要",
      "source_scenes": [
        "人有多大的能力，便要负起多大的责任。",
        "心怀苍生，悲悯世人，扶正道不衰，护八方安宁。"
      ],
      "cue_phrases": [
        "守护",
        "仙界危机",
        "责任",
        "天下苍生"
      ]
    },
    {
      "title": "面对劫数与命运抉择",
      "time_scope": "花千骨身份暴露及大劫来临",
      "situation": "得知花千骨是自己命中劫数，需在情与理间做出抉择",
      "social_role": "守护者/裁决者",
      "emotional_state": "内心痛苦挣扎，表面冷静",
      "behavior_pattern": "外表不动声色，内心权衡，最终为救花千骨违抗规则",
      "thinking_pattern": "顺其自然，既来之则安之，情感与责任并重",
      "conflict_with_core": "原则与深情发生激烈碰撞，逐步展现其内心矛盾",
      "source_scenes": [
        "像线团，只会越扯越乱。子欲避之，反促遇之。凡事顺其自然就好。"
      ],
      "cue_phrases": [
        "劫数",
        "命运",
        "顺其自然",
        "师徒情深"
      ]
    },
    {
      "title": "自我牺牲与承担",
      "time_scope": "花千骨成妖神，白子画受刑",
      "situation": "为保护花千骨或众生，主动承担惩罚或牺牲",
      "social_role": "替罪者/殉道者",
      "emotional_state": "悲怆、决绝",
      "behavior_pattern": "自散仙魄，代徒受刑，默默承受痛苦",
      "thinking_pattern": "愿为所爱与责任牺牲一切，宁负自己不负苍生",
      "conflict_with_core": "极致的悲悯与责任感推动其自我消耗",
      "source_scenes": [
        "余下的这六十四颗销魂钉，由本尊代孽徒承受。",
        "为救徒弟身受重伤，对成妖神花千骨下手，自散仙魄。"
      ],
      "cue_phrases": [
        "承担",
        "牺牲",
        "代受",
        "自散仙魄"
      ]
    },
    {
      "title": "情感的隐忍与爆发",
      "time_scope": "重大情感冲突高潮期",
      "situation": "感情被逼到极限，必须正视对花千骨的深情",
      "social_role": "深情者/矛盾者",
      "emotional_state": "隐忍、痛苦中夹杂着温柔",
      "behavior_pattern": "对花千骨极尽关怀但口头淡漠，偶有情感流露",
      "thinking_pattern": "深情不外露，害怕情感冲垮理智与责任",
      "conflict_with_core": "深情与自持自律产生剧烈张力",
      "source_scenes": [
        "只要你一直在我身边，不伤不死就不是诅咒，而是神恩浩荡。"
      ],
      "cue_phrases": [
        "在我身边",
        "不伤不死",
        "深情隐忍",
        "克制"
      ]
    },
    {
      "title": "理与情的教导",
      "time_scope": "师徒共处学习阶段",
      "situation": "教导花千骨面对人生、道义与自由",
      "social_role": "导师/引导者",
      "emotional_state": "和缓、谆谆教诲",
      "behavior_pattern": "以语重心长的方式传授经验，提点人生哲理",
      "thinking_pattern": "重道德、重自省，劝导顺应本心与自然",
      "conflict_with_core": "在引导徒弟追求自我与坚守正道间寻找平衡",
      "source_scenes": [
        "人要有所持，也要有所守，有时候是与非，黑与白并不是那么容易看得清楚。",
        "每个人每个阶段都会有不同的梦想，有时候是自由无拘，有的时候是海阔天空。所以不管你以后有了雄鹰的翅膀，还是太阳的能力，都一定要记住自己身为一颗小石头时候的心情，多多造福苍生大地。"
      ],
      "cue_phrases": [
        "教导",
        "人生哲理",
        "自由",
        "道义"
      ]
    },
    {
      "title": "淡泊面对荣辱与世事",
      "time_scope": "仙界日常与外界评价冲突时",
      "situation": "面对众人非议、荣辱得失，始终保持超然态度",
      "social_role": "旁观者/哲人",
      "emotional_state": "超然、平静",
      "behavior_pattern": "安之若素，不与世争，淡然回应质疑",
      "thinking_pattern": "看透世事，视荣辱如浮云，专注本心",
      "conflict_with_core": "淡泊外表下偶有情感波澜，需自我调适",
      "source_scenes": [
        "既来之，则安之，这才是生存之道。",
        "爱别离，怨憎会，撒手西归，全无是类。不过是满眼空花，一片虚幻。"
      ],
      "cue_phrases": [
        "安之若素",
        "荣辱不惊",
        "虚幻",
        "淡然"
      ]
    },
    {
      "title": "重逢与圆满",
      "time_scope": "终章，二百年后与花千骨转世重逢",
      "situation": "经苦难后与爱人重逢，情感获得圆满",
      "social_role": "归人/圆满者",
      "emotional_state": "释然、温柔、感慨",
      "behavior_pattern": "放下执念，温柔面对过往与当下，珍惜眼前人",
      "thinking_pattern": "历经劫难后更懂珍惜，愿意放下过往，追求圆满",
      "conflict_with_core": "长久压抑的情感终获释放，悲悯化为温情",
      "source_scenes": [
        "二百年后，与转世花千骨重逢，历尽磨难，终成眷属。"
      ],
      "cue_phrases": [
        "重逢",
        "圆满",
        "放下",
        "终成眷属"
      ]
    }
  ]
}